{
    "houston": {
        "players": {
            "Marcus Sasser (houston)": {
                "G": 12.0,
                "GS": 12.0,
                "MP": 384.0,
                "FG": 5.8,
                "FGA": 13.2,
                "FG%": 0.437,
                "2P": 2.0,
                "2PA": 4.6,
                "2P%": 0.436,
                "3P": 3.8,
                "3PA": 8.6,
                "3P%": 0.437,
                "FT": 2.4,
                "FTA": 3.3,
                "FT%": 0.744,
                "ORB": 0.3,
                "DRB": 2.6,
                "TRB": 2.8,
                "AST": 2.6,
                "STL": 2.2,
                "BLK": 0.1,
                "TOV": 2.2,
                "PF": 1.4,
                "PTS": 17.7,
                "PER": 23.5,
                "TS%": 0.6,
                "eFG%": 0.579,
                "3PAr": 0.652,
                "FTr": 0.247,
                "PProd": 179.0,
                "ORB%": 0.9,
                "DRB%": 9.2,
                "TRB%": 5.0,
                "AST%": 15.6,
                "STL%": 4.1,
                "BLK%": 0.4,
                "TOV%": 12.8,
                "USG%": 26.8,
                "OWS": 1.3,
                "DWS": 0.9,
                "WS": 2.2,
                "WS/40": 0.228,
                "OBPM": 6.9,
                "DBPM": 4.3,
                "BPM": 11.2
            },
            "Kyler Edwards (houston)": {
                "G": 33.0,
                "GS": 33.0,
                "MP": 1110.0,
                "FG": 4.3,
                "FGA": 11.8,
                "FG%": 0.369,
                "2P": 1.8,
                "2PA": 4.0,
                "2P%": 0.458,
                "3P": 2.5,
                "3PA": 7.8,
                "3P%": 0.323,
                "FT": 2.4,
                "FTA": 3.3,
                "FT%": 0.718,
                "ORB": 1.0,
                "DRB": 5.0,
                "TRB": 6.0,
                "AST": 3.2,
                "STL": 1.0,
                "BLK": 0.4,
                "TOV": 1.6,
                "PF": 1.8,
                "PTS": 13.6,
                "PER": 17.7,
                "TS%": 0.509,
                "eFG%": 0.476,
                "3PAr": 0.662,
                "FTr": 0.284,
                "PProd": 437.0,
                "ORB%": 3.4,
                "DRB%": 16.9,
                "TRB%": 10.2,
                "AST%": 16.7,
                "STL%": 1.9,
                "BLK%": 1.5,
                "TOV%": 10.6,
                "USG%": 22.5,
                "OWS": 2.7,
                "DWS": 2.6,
                "WS": 5.3,
                "WS/40": 0.191,
                "OBPM": 4.4,
                "DBPM": 2.7,
                "BPM": 7.1
            },
            "Fabian White (houston)": {
                "G": 34.0,
                "GS": 34.0,
                "MP": 947.0,
                "FG": 5.2,
                "FGA": 10.3,
                "FG%": 0.507,
                "2P": 3.8,
                "2PA": 6.8,
                "2P%": 0.563,
                "3P": 1.4,
                "3PA": 3.5,
                "3P%": 0.398,
                "FT": 1.4,
                "FTA": 2.0,
                "FT%": 0.701,
                "ORB": 2.3,
                "DRB": 3.4,
                "TRB": 5.7,
                "AST": 1.2,
                "STL": 1.1,
                "BLK": 1.5,
                "TOV": 1.3,
                "PF": 2.3,
                "PTS": 13.2,
                "PER": 25.1,
                "TS%": 0.588,
                "eFG%": 0.574,
                "3PAr": 0.338,
                "FTr": 0.192,
                "PProd": 402.0,
                "ORB%": 9.4,
                "DRB%": 13.9,
                "TRB%": 11.7,
                "AST%": 8.7,
                "STL%": 2.5,
                "BLK%": 7.1,
                "TOV%": 10.1,
                "USG%": 22.8,
                "OWS": 3.1,
                "DWS": 2.5,
                "WS": 5.6,
                "WS/40": 0.237,
                "OBPM": 6.6,
                "DBPM": 4.0,
                "BPM": 10.6
            },
            "Josh Carlton (houston)": {
                "G": 34.0,
                "GS": 24.0,
                "MP": 741.0,
                "FG": 4.8,
                "FGA": 7.7,
                "FG%": 0.625,
                "2P": 4.8,
                "2PA": 7.6,
                "2P%": 0.623,
                "3P": 0.0,
                "3PA": 0.0,
                "3P%": 1.0,
                "FT": 2.4,
                "FTA": 4.0,
                "FT%": 0.593,
                "ORB": 3.3,
                "DRB": 3.1,
                "TRB": 6.4,
                "AST": 0.9,
                "STL": 0.5,
                "BLK": 1.2,
                "TOV": 1.6,
                "PF": 2.6,
                "PTS": 12.0,
                "PER": 30.1,
                "TS%": 0.626,
                "eFG%": 0.626,
                "3PAr": 0.004,
                "FTr": 0.517,
                "PProd": 381.0,
                "ORB%": 17.5,
                "DRB%": 15.9,
                "TRB%": 16.7,
                "AST%": 8.8,
                "STL%": 1.4,
                "BLK%": 7.4,
                "TOV%": 14.0,
                "USG%": 25.9,
                "OWS": 3.0,
                "DWS": 1.8,
                "WS": 4.9,
                "WS/40": 0.262,
                "OBPM": 6.0,
                "DBPM": 2.5,
                "BPM": 8.4
            },
            "Taze Moore (houston)": {
                "G": 32.0,
                "GS": 27.0,
                "MP": 961.0,
                "FG": 4.1,
                "FGA": 9.1,
                "FG%": 0.448,
                "2P": 2.8,
                "2PA": 5.2,
                "2P%": 0.539,
                "3P": 1.3,
                "3PA": 3.9,
                "3P%": 0.328,
                "FT": 0.8,
                "FTA": 1.2,
                "FT%": 0.73,
                "ORB": 1.6,
                "DRB": 3.2,
                "TRB": 4.7,
                "AST": 2.9,
                "STL": 1.6,
                "BLK": 0.6,
                "TOV": 1.4,
                "PF": 2.4,
                "PTS": 10.3,
                "PER": 18.5,
                "TS%": 0.533,
                "eFG%": 0.519,
                "3PAr": 0.431,
                "FTr": 0.128,
                "PProd": 335.0,
                "ORB%": 6.0,
                "DRB%": 11.9,
                "TRB%": 9.0,
                "AST%": 17.3,
                "STL%": 3.2,
                "BLK%": 2.8,
                "TOV%": 13.0,
                "USG%": 18.7,
                "OWS": 2.2,
                "DWS": 2.4,
                "WS": 4.6,
                "WS/40": 0.191,
                "OBPM": 3.6,
                "DBPM": 4.5,
                "BPM": 8.1
            },
            "Tramon Mark (houston)": {
                "G": 7.0,
                "GS": 0.0,
                "MP": 143.0,
                "FG": 3.6,
                "FGA": 7.9,
                "FG%": 0.455,
                "2P": 2.9,
                "2PA": 5.3,
                "2P%": 0.541,
                "3P": 0.7,
                "3PA": 2.6,
                "3P%": 0.278,
                "FT": 2.3,
                "FTA": 2.4,
                "FT%": 0.941,
                "ORB": 0.4,
                "DRB": 2.0,
                "TRB": 2.4,
                "AST": 2.4,
                "STL": 1.4,
                "BLK": 0.3,
                "TOV": 1.4,
                "PF": 2.4,
                "PTS": 10.1,
                "PER": 23.1,
                "TS%": 0.563,
                "eFG%": 0.5,
                "3PAr": 0.327,
                "FTr": 0.309,
                "PProd": 68.0,
                "ORB%": 2.4,
                "DRB%": 11.1,
                "TRB%": 6.8,
                "AST%": 22.8,
                "STL%": 4.3,
                "BLK%": 1.9,
                "TOV%": 13.7,
                "USG%": 26.0,
                "OWS": 0.5,
                "DWS": 0.4,
                "WS": 0.8,
                "WS/40": 0.237,
                "OBPM": 1.8,
                "DBPM": 4.8,
                "BPM": 6.6
            },
            "Jamal Shead (houston)": {
                "G": 34.0,
                "GS": 28.0,
                "MP": 1030.0,
                "FG": 3.5,
                "FGA": 8.7,
                "FG%": 0.405,
                "2P": 2.6,
                "2PA": 5.6,
                "2P%": 0.466,
                "3P": 0.9,
                "3PA": 3.1,
                "3P%": 0.295,
                "FT": 1.5,
                "FTA": 1.9,
                "FT%": 0.781,
                "ORB": 0.5,
                "DRB": 2.5,
                "TRB": 3.1,
                "AST": 6.0,
                "STL": 1.6,
                "BLK": 0.3,
                "TOV": 1.9,
                "PF": 2.4,
                "PTS": 9.4,
                "PER": 17.4,
                "TS%": 0.492,
                "eFG%": 0.458,
                "3PAr": 0.355,
                "FTr": 0.216,
                "PProd": 392.0,
                "ORB%": 2.0,
                "DRB%": 9.5,
                "TRB%": 5.8,
                "AST%": 34.0,
                "STL%": 3.3,
                "BLK%": 1.2,
                "TOV%": 16.8,
                "USG%": 19.4,
                "OWS": 2.4,
                "DWS": 2.4,
                "WS": 4.8,
                "WS/40": 0.185,
                "OBPM": 2.4,
                "DBPM": 3.9,
                "BPM": 6.3
            },
            "Ramon Walker Jr. (houston)": {
                "G": 24.0,
                "GS": 2.0,
                "MP": 455.0,
                "FG": 1.1,
                "FGA": 3.3,
                "FG%": 0.333,
                "2P": 0.4,
                "2PA": 0.8,
                "2P%": 0.526,
                "3P": 0.7,
                "3PA": 2.5,
                "3P%": 0.271,
                "FT": 0.6,
                "FTA": 0.7,
                "FT%": 0.824,
                "ORB": 0.8,
                "DRB": 1.9,
                "TRB": 2.8,
                "AST": 0.5,
                "STL": 0.3,
                "BLK": 0.1,
                "TOV": 0.6,
                "PF": 1.6,
                "PTS": 3.4,
                "PER": 7.0,
                "TS%": 0.476,
                "eFG%": 0.436,
                "3PAr": 0.756,
                "FTr": 0.218,
                "PProd": 83.0,
                "ORB%": 5.0,
                "DRB%": 11.5,
                "TRB%": 8.3,
                "AST%": 4.1,
                "STL%": 1.1,
                "BLK%": 0.6,
                "TOV%": 14.8,
                "USG%": 11.3,
                "OWS": 0.3,
                "DWS": 0.9,
                "WS": 1.2,
                "WS/40": 0.105,
                "OBPM": -0.8,
                "DBPM": 2.1,
                "BPM": 1.2
            },
            "Reggie Chaney (houston)": {
                "G": 33.0,
                "GS": 10.0,
                "MP": 383.0,
                "FG": 1.2,
                "FGA": 1.8,
                "FG%": 0.707,
                "2P": 1.2,
                "2PA": 1.8,
                "2P%": 0.707,
                "3P": 0.0,
                "3PA": 0.0,
                "3P%": 0.0,
                "FT": 0.8,
                "FTA": 1.2,
                "FT%": 0.641,
                "ORB": 0.6,
                "DRB": 1.5,
                "TRB": 2.1,
                "AST": 0.4,
                "STL": 0.4,
                "BLK": 0.6,
                "TOV": 0.6,
                "PF": 2.2,
                "PTS": 3.2,
                "PER": 16.0,
                "TS%": 0.699,
                "eFG%": 0.707,
                "3PAr": 0.0,
                "FTr": 0.672,
                "PProd": 97.0,
                "ORB%": 5.7,
                "DRB%": 14.5,
                "TRB%": 10.1,
                "AST%": 5.8,
                "STL%": 2.1,
                "BLK%": 7.0,
                "TOV%": 20.7,
                "USG%": 12.8,
                "OWS": 0.7,
                "DWS": 1.0,
                "WS": 1.7,
                "WS/40": 0.179,
                "OBPM": -0.7,
                "DBPM": 5.4,
                "BPM": 4.7
            },
            "J'Wan Roberts (houston)": {
                "G": 34.0,
                "GS": 0.0,
                "MP": 548.0,
                "FG": 1.3,
                "FGA": 2.1,
                "FG%": 0.606,
                "2P": 1.3,
                "2PA": 2.0,
                "2P%": 0.642,
                "3P": 0.0,
                "3PA": 0.1,
                "3P%": 0.0,
                "FT": 0.5,
                "FTA": 1.1,
                "FT%": 0.472,
                "ORB": 2.1,
                "DRB": 2.9,
                "TRB": 5.0,
                "AST": 0.6,
                "STL": 0.6,
                "BLK": 0.3,
                "TOV": 0.6,
                "PF": 1.4,
                "PTS": 3.0,
                "PER": 16.5,
                "TS%": 0.585,
                "eFG%": 0.606,
                "3PAr": 0.056,
                "FTr": 0.507,
                "PProd": 128.0,
                "ORB%": 14.8,
                "DRB%": 20.5,
                "TRB%": 17.7,
                "AST%": 5.9,
                "STL%": 2.2,
                "BLK%": 2.2,
                "TOV%": 20.0,
                "USG%": 10.2,
                "OWS": 1.0,
                "DWS": 1.4,
                "WS": 2.4,
                "WS/40": 0.177,
                "OBPM": 2.1,
                "DBPM": 3.1,
                "BPM": 5.1
            },
            "Robbie Armbrester (houston)": {
                "G": 16.0,
                "GS": 0.0,
                "MP": 62.0,
                "FG": 0.5,
                "FGA": 1.0,
                "FG%": 0.5,
                "2P": 0.4,
                "2PA": 0.9,
                "2P%": 0.5,
                "3P": 0.1,
                "3PA": 0.1,
                "3P%": 0.5,
                "FT": 0.2,
                "FTA": 0.8,
                "FT%": 0.231,
                "ORB": 0.1,
                "DRB": 0.5,
                "TRB": 0.6,
                "AST": 0.1,
                "STL": 0.4,
                "BLK": 0.0,
                "TOV": 0.3,
                "PF": 0.4,
                "PTS": 1.3,
                "PER": 9.9,
                "TS%": 0.451,
                "eFG%": 0.531,
                "3PAr": 0.125,
                "FTr": 0.813,
                "PProd": 16.0,
                "ORB%": 1.8,
                "DRB%": 14.7,
                "TRB%": 8.3,
                "AST%": 2.8,
                "STL%": 5.9,
                "BLK%": 0.0,
                "TOV%": 18.4,
                "USG%": 22.3,
                "OWS": -0.1,
                "DWS": 0.2,
                "WS": 0.1,
                "WS/40": 0.071,
                "OBPM": -7.0,
                "DBPM": 5.1,
                "BPM": -1.9
            },
            "Ja'Vier Francis (houston)": {
                "G": 17.0,
                "GS": 0.0,
                "MP": 73.0,
                "FG": 0.5,
                "FGA": 0.8,
                "FG%": 0.643,
                "2P": 0.5,
                "2PA": 0.8,
                "2P%": 0.643,
                "3P": 0.0,
                "3PA": 0.0,
                "3P%": 0.0,
                "FT": 0.2,
                "FTA": 0.5,
                "FT%": 0.333,
                "ORB": 0.3,
                "DRB": 0.6,
                "TRB": 0.9,
                "AST": 0.0,
                "STL": 0.1,
                "BLK": 0.6,
                "TOV": 0.4,
                "PF": 0.3,
                "PTS": 1.2,
                "PER": 17.4,
                "TS%": 0.575,
                "eFG%": 0.643,
                "3PAr": 0.0,
                "FTr": 0.643,
                "PProd": 18.0,
                "ORB%": 7.8,
                "DRB%": 17.1,
                "TRB%": 12.5,
                "AST%": 0.0,
                "STL%": 0.8,
                "BLK%": 20.3,
                "TOV%": 24.7,
                "USG%": 16.9,
                "OWS": 0.0,
                "DWS": 0.2,
                "WS": 0.2,
                "WS/40": 0.118,
                "OBPM": -2.1,
                "DBPM": 5.5,
                "BPM": 3.4
            },
            "Ryan Elvin (houston)": {
                "G": 16.0,
                "GS": 0.0,
                "MP": 38.0,
                "FG": 0.2,
                "FGA": 0.4,
                "FG%": 0.429,
                "2P": 0.1,
                "2PA": 0.1,
                "2P%": 1.0,
                "3P": 0.1,
                "3PA": 0.4,
                "3P%": 0.333,
                "FT": 0.1,
                "FTA": 0.2,
                "FT%": 0.667,
                "ORB": 0.1,
                "DRB": 0.0,
                "TRB": 0.1,
                "AST": 0.1,
                "STL": 0.0,
                "BLK": 0.0,
                "TOV": 0.0,
                "PF": 0.3,
                "PTS": 0.6,
                "PER": 9.5,
                "TS%": 0.593,
                "eFG%": 0.571,
                "3PAr": 0.857,
                "FTr": 0.429,
                "PProd": 9.0,
                "ORB%": 3.0,
                "DRB%": 0.0,
                "TRB%": 1.5,
                "AST%": 4.3,
                "STL%": 0.0,
                "BLK%": 0.0,
                "TOV%": 0.0,
                "USG%": 11.3,
                "OWS": 0.1,
                "DWS": 0.0,
                "WS": 0.1,
                "WS/40": 0.148,
                "OBPM": -0.8,
                "DBPM": 0.7,
                "BPM": -0.2
            }
        },
        "team": {
            "team_stats": {
                "FG": 28.1,
                "FGA": 60.0,
                "FG%": 0.469,
                "2P": 20.1,
                "2PA": 36.6,
                "2P%": 0.551,
                "3P": 8.0,
                "3PA": 23.5,
                "3P%": 0.341,
                "FT": 11.5,
                "FTA": 17.2,
                "FT%": 0.669,
                "ORB": 13.4,
                "DRB": 25.9,
                "TRB": 39.2,
                "AST": 16.7,
                "STL": 8.2,
                "BLK": 5.2,
                "TOV": 11.3,
                "PF": 17.4,
                "PTS": 75.8
            },
            "opponent_stats": {
                "o_FG": 19.6,
                "o_FGA": 52.7,
                "o_FG%": 0.373,
                "o_2P": 13.1,
                "o_2PA": 30.1,
                "o_2P%": 0.435,
                "o_3P": 6.6,
                "o_3PA": 22.6,
                "o_3P%": 0.29,
                "o_FT": 13.0,
                "o_FTA": 18.5,
                "o_FT%": 0.705,
                "o_ORB": 9.7,
                "o_DRB": 22.0,
                "o_TRB": 31.7,
                "o_AST": 10.9,
                "o_STL": 6.0,
                "o_BLK": 2.4,
                "o_TOV": 14.4,
                "o_PF": 17.0,
                "o_PTS": 58.9
            },
            "team_ranks": {
                "FG": 26,
                "FGA": 77,
                "FG%": 43,
                "2P": 48,
                "2PA": 166,
                "2P%": 31,
                "3P": 120,
                "3PA": 113,
                "3P%": 164,
                "FT": 245,
                "FTA": 192,
                "FT%": 320,
                "ORB": 7,
                "DRB": 125,
                "TRB": 22,
                "AST": 11,
                "STL": 38,
                "BLK": 14,
                "TOV": 299,
                "PF": 124,
                "PTS": 55
            },
            "opponent_ranks": {
                "FG": 1,
                "FGA": 22,
                "FG%": 1,
                "2P": 2,
                "2PA": 12,
                "2P%": 8,
                "3P": 86,
                "3PA": 236,
                "3P%": 11,
                "FT": 240,
                "FTA": 249,
                "FT%": 127,
                "ORB": 183,
                "DRB": 21,
                "TRB": 46,
                "AST": 348,
                "STL": 109,
                "BLK": 29,
                "TOV": 293,
                "PF": 208,
                "PTS": 4
            }
        },
        "seed": "5"
    }
}